swaglib/__init__.py
swaglib/modules.py
swaglib-0.1.8.dist-info/licenses/LICENSE
swaglib-0.1.8.dist-info/METADATA
swaglib-0.1.8.dist-info/WHEEL
swaglib-0.1.8.dist-info/top_level.txt
swaglib-0.1.8.dist-info/RECORD
