Metadata-Version: 2.4
Name: swaglib
Version: 0.1.8
Summary: swaglib.
Author-email: nomaakip <nomaakip@gmail.com>
License-Expression: MIT
Project-URL: Homepage, https://github.com/Freakybob-Team/swaglib
Project-URL: Documentation, https://github.com/Freakybob-Team/swaglib
Project-URL: Repository, https://github.com/Freakybob-Team/swaglib
Project-URL: Issues, https://github.com/Freakybob-Team/swaglib/issues
Requires-Python: >=3.13
License-File: LICENSE
Requires-Dist: requests
Dynamic: license-file
